{
	"videoinfo": {
		"aid": 10277849,
		"title": "【剧场版】3年E班剧场版 365天的时间【生肉/720P】",
		"video_review": 2509,
		"duration": null,
		"tag": "日本动画,剧场版,3年E班,福山润,720P",
		"description": "http://盘.baidu.com/s/1i4PiUKd 密码：7inh\n召唤字幕菌字幕组\n感谢贴吧吧友",
		"tid": 33,
		"typename": "连载动画",
		"created": 1493789390,
		"created_at": "2017/05/03 13:29",
		"author": "躲在树上吃翔",
		"mid": 5977857,
		"play": 117435,
		"coins": 688,
		"review": 224,
		"favorites": 5987,
		"synctime": 1568314469.26495,
		"lpartinfo": [
			{
				"cid": 16981205,
				"page": 1,
				"title": "av10277849",
				"aid": 10277849,
				"duration": 5543,
				"video_review": 2509
			}
		]
	},
	"partlist": [
		{
			"cid": 16981205,
			"page": 1,
			"from": "vupload",
			"part": "",
			"duration": 5543,
			"vid": "",
			"weblink": "",
			"dimension": {
				"width": 0,
				"height": 0,
				"rotate": 0
			}
		}
	],
	"source": "bpd",
	"page": "<!DOCTYPE html><html><head itemprop=\"video\" itemscope itemtype=\"http://schema.org/VideoObject\"><title data-vue-meta=\"true\">【剧场版】3年E班剧场版 365天的时间【生肉/720P】_哔哩哔哩 (゜-゜)つロ 干杯~-bilibili</title> <meta data-vue-meta=\"true\" http-equiv=\"Content-Type\" content=\"text/html\" charset=\"utf-8\"><meta data-vue-meta=\"true\" name=\"renderer\" content=\"webkit\"><meta data-vue-meta=\"true\" http-equiv=\"X-UA-Compatible\" content=\"IE=edge\"><meta data-vue-meta=\"true\" name=\"spm_prefix\" content=\"333.788\"><meta data-vue-meta=\"true\" itemprop=\"keywords\" name=\"keywords\" content=\"【剧场版】3年E班剧场版 365天的时间【生肉/720P】,剧场版,日本动画,3年E班,福山润,720P,番剧,连载动画,哔哩哔哩,Bilibili,B站,弹幕\"><meta data-vue-meta=\"true\" itemprop=\"description\" name=\"description\" content=\"http://盘.baidu.com/s/1i4PiUKd 密码：7inh召唤字幕菌字幕组感谢贴吧吧友\"><meta data-vue-meta=\"true\" itemprop=\"author\" name=\"author\" content=\"躲在树上吃翔\"><meta data-vue-meta=\"true\" itemprop=\"name\" name=\"title\" content=\"【剧场版】3年E班剧场版 365天的时间【生肉/720P】_哔哩哔哩 (゜-゜)つロ 干杯~-bilibili\"><meta data-vue-meta=\"true\" itemprop=\"url\" content=\"https://www.bilibili.com/video/av10277849/\"><meta data-vue-meta=\"true\" itemprop=\"image\" content=\"http://i2.hdslb.com/bfs/archive/97d1a78678670de942ef5ef64be75725cb56f85b.jpg\"><meta data-vue-meta=\"true\" itemprop=\"thumbnailUrl\" content=\"http://i2.hdslb.com/bfs/archive/97d1a78678670de942ef5ef64be75725cb56f85b.jpg\"><meta data-vue-meta=\"true\" itemprop=\"uploadDate\" content=\"2017-05-03 13:29:50\"><meta data-vue-meta=\"true\" itemprop=\"datePublished\" content=\"2017-06-14 16:35:49\"><meta data-vue-meta=\"true\" itemprop=\"comment\" content=\"做了七分钟的字幕……很累的我放弃了,熟肉av10286846（顶上去造福大家）qwq,被骗了无数次眼泪…\"><meta data-vue-meta=\"true\" itemprop=\"commentCount\" content=\"225\"><meta data-vue-meta=\"true\" property=\"og:type\" content=\"video\"><meta data-vue-meta=\"true\" property=\"og:title\" content=\"【剧场版】3年E班剧场版 365天的时间【生肉/720P】_哔哩哔哩 (゜-゜)つロ 干杯~-bilibili\"><meta data-vue-meta=\"true\" property=\"og:image\" content=\"http://i2.hdslb.com/bfs/archive/97d1a78678670de942ef5ef64be75725cb56f85b.jpg\"><meta data-vue-meta=\"true\" property=\"og:url\" content=\"https://www.bilibili.com/video/av10277849/\"><meta data-vue-meta=\"true\" property=\"og:width\" content=\"846\"><meta data-vue-meta=\"true\" property=\"og:height\" content=\"566\"> <link data-vue-meta=\"true\" rel=\"canonical\" href=\"https://www.bilibili.com/video/av10277849/\"><script type=\"text/javascript\">!function(){for(var o=window.navigator.userAgent,i=[\"Android\",\"iPhone\",\"SymbianOS\",\"Windows Phone\",\"iPod\"],r=!0,a=0,n=i.length;a<n;a++)if(0<o.indexOf(i[a])){r=!1;break}if(!r){var e=window.location.origin.replace(\"www\",\"m\")+\"/video/\"+window.location.href.match(/av([0-9]+)/g)[0]+\".html\"+window.location.search;window.location.href=e}}(),window.spmReportData={},window.reportConfig={sample:1,scrollTracker:!0,msgObjects:\"spmReportData\",errorTracker:!0,hasAbtest:!0,abtestPlatform:4}</script><style>.ie-fix{background:#fff;position:fixed;left:0;top:0;right:0;bottom:0;width:100%;height:100%;z-index:9999999}.ie-fix .title{background:#00a1d6;text-align:center;padding:10px 0;color:#fff}</style><script>window.__INITIAL_STATE__={\"aid\":\"10277849\",\"p\":\"\",\"videoData\":{\"aid\":10277849,\"videos\":1,\"tid\":33,\"tname\":\"连载动画\",\"copyright\":2,\"pic\":\"http:\\u002F\\u002Fi2.hdslb.com\\u002Fbfs\\u002Farchive\\u002F97d1a78678670de942ef5ef64be75725cb56f85b.jpg\",\"title\":\"【剧场版】3年E班剧场版 365天的时间【生肉\\u002F720P】\",\"pubdate\":1493789390,\"ctime\":1497429349,\"desc\":\"http:\\u002F\\u002F盘.baidu.com\\u002Fs\\u002F1i4PiUKd 密码：7inh\\n召唤字幕菌字幕组\\n感谢贴吧吧友\",\"state\":0,\"attribute\":49152,\"duration\":5542,\"rights\":{\"bp\":0,\"elec\":0,\"download\":1,\"movie\":0,\"pay\":0,\"hd5\":0,\"no_reprint\":0,\"autoplay\":1,\"ugc_pay\":0,\"is_cooperation\":0,\"ugc_pay_preview\":0},\"owner\":{\"mid\":5977857,\"name\":\"躲在树上吃翔\",\"face\":\"http:\\u002F\\u002Fi2.hdslb.com\\u002Fbfs\\u002Fface\\u002F5c50543c47eb74ad6ad03a0b709be21ab70133fd.jpg\"},\"stat\":{\"aid\":10277849,\"view\":\"--\",\"danmaku\":\"--\",\"reply\":225,\"favorite\":\"--\",\"coin\":\"--\",\"share\":\"--\",\"now_rank\":0,\"his_rank\":0,\"like\":\"--\",\"dislike\":0},\"dynamic\":\"\",\"cid\":16981205,\"dimension\":{\"width\":0,\"height\":0,\"rotate\":0},\"no_cache\":true,\"pages\":[{\"cid\":16981205,\"page\":1,\"from\":\"vupload\",\"part\":\"\",\"duration\":5543,\"vid\":\"\",\"weblink\":\"\",\"dimension\":{\"width\":0,\"height\":0,\"rotate\":0}}],\"subtitle\":{\"allow_submit\":false,\"list\":[]},\"embedPlayer\":\"EmbedPlayer(\\\"player\\\", \\\"\\u002F\\u002Fs1.hdslb.com\\u002Fbfs\\u002Fstatic\\u002Fplayer\\u002Fmain\\u002Fflash\\u002Fplay.swf\\\", \\\"cid=16981205&aid=10277849&attribute=49152\\\")\"},\"upData\":{\"mid\":\"5977857\",\"name\":\"躲在树上吃翔\",\"approve\":false,\"sex\":\"保密\",\"rank\":\"10000\",\"face\":\"http:\\u002F\\u002Fi2.hdslb.com\\u002Fbfs\\u002Fface\\u002F5c50543c47eb74ad6ad03a0b709be21ab70133fd.jpg\",\"DisplayRank\":\"0\",\"regtime\":0,\"spacesta\":0,\"birthday\":\"\",\"place\":\"\",\"description\":\"\",\"article\":0,\"attentions\":[],\"fans\":462,\"friend\":501,\"attention\":501,\"sign\":\"我还是支持拜仁慕尼黑\",\"level_info\":{\"current_level\":5,\"current_min\":0,\"current_exp\":0,\"next_exp\":0},\"pendant\":{\"pid\":0,\"name\":\"\",\"image\":\"\",\"expire\":0},\"nameplate\":{\"nid\":74,\"name\":\"大会员2018年度勋章\",\"image\":\"http:\\u002F\\u002Fi0.hdslb.com\\u002Fbfs\\u002Fface\\u002F421179426c929dfeaed4117461c83f5d07ffb148.png\",\"image_small\":\"http:\\u002F\\u002Fi0.hdslb.com\\u002Fbfs\\u002Fface\\u002F682001c2e1c2ae887bdf2a0e18eef61180c48f84.png\",\"level\":\"稀有勋章\",\"condition\":\"2018.6.26-7.8某一天是年度大会员\"},\"Official\":{\"role\":0,\"title\":\"\",\"desc\":\"\"},\"official_verify\":{\"type\":-1,\"desc\":\"\"},\"vip\":{\"vipType\":2,\"dueRemark\":\"\",\"accessStatus\":0,\"vipStatus\":1,\"vipStatusWarn\":\"\",\"theme_type\":0},\"archiveCount\":2},\"staffData\":[],\"tags\":[{\"tag_id\":1663,\"tag_name\":\"剧场版\",\"cover\":\"\",\"head_cover\":\"\",\"content\":\"\",\"short_content\":\"\",\"type\":3,\"state\":0,\"ctime\":1436866637,\"count\":{\"view\":0,\"use\":28981,\"atten\":56723},\"is_atten\":0,\"likes\":2,\"hates\":0,\"attribute\":0,\"liked\":0,\"hated\":0,\"showDetail\":false,\"showReport\":false,\"timeOut\":null},{\"tag_id\":63700,\"tag_name\":\"日本动画\",\"cover\":\"\",\"head_cover\":\"\",\"content\":\"\",\"short_content\":\"\",\"type\":3,\"state\":0,\"ctime\":1436866637,\"count\":{\"view\":0,\"use\":45726,\"atten\":51704},\"is_atten\":0,\"likes\":2,\"hates\":0,\"attribute\":0,\"liked\":0,\"hated\":0,\"showDetail\":false,\"showReport\":false,\"timeOut\":null},{\"tag_id\":1564710,\"tag_name\":\"3年E班\",\"cover\":\"\",\"head_cover\":\"\",\"content\":\"\",\"short_content\":\"\",\"type\":3,\"state\":0,\"ctime\":1455467081,\"count\":{\"view\":0,\"use\":357,\"atten\":429},\"is_atten\":0,\"likes\":2,\"hates\":0,\"attribute\":0,\"liked\":0,\"hated\":0,\"showDetail\":false,\"showReport\":false,\"timeOut\":null},{\"tag_id\":5911,\"tag_name\":\"福山润\",\"cover\":\"http:\\u002F\\u002Fi0.hdslb.com\\u002Fbfs\\u002Ftag\\u002F6e6d00e427f1d70d61beaae8877cd50cb8d8751a.jpg\",\"head_cover\":\"\",\"content\":\"福山润（1978年11月26日－），日本著名男性声优。生于广岛县福山市，出身于大阪府高槻市。AXL ONE事务所所属。身高170cm、体重53kg、血型A型、星座是射手座。在2000－2001年的《无敌王TRI-ZENON》中初次担任主角，饰演神威章。2006年荣获日本“文化放送”最佳男声优奖。令福山润真正登上事业上第一次巅峰的角色是《CODE GEASS 》中的腹黑王子鲁路修·兰佩路基，他也凭该角色获得了第一届日本声优大赏“主演男声优奖”。2009年荣获第八届“东京アニメアワード”最佳声优奖。2009年荣获第三届日本声优大赏“海外ファン赏”。2011年、辞退长年所属的PRODUCTION baobab事务所、和森川智之共同设立AXL ONE事务所。其他代表作：阿尔贝（岩窟王）、四月一日君寻（×××HOLiC）、志水桂一（金色琴弦）、葵·托利（境界线上的地平线）、富樫勇太（中二病也要谈恋爱！）、熊猫（白熊咖啡馆）、克拉福·罗伦斯（狼与香辛料）、奴良陆生（滑头鬼之孙）、格雷尔·萨特克利夫（黑执事）、奥村雪男（青之驱魔师）。\",\"short_content\":\"\",\"type\":3,\"state\":0,\"ctime\":1436866637,\"count\":{\"view\":0,\"use\":5275,\"atten\":14460},\"is_atten\":0,\"likes\":0,\"hates\":0,\"attribute\":0,\"liked\":0,\"hated\":0,\"showDetail\":false,\"showReport\":false,\"timeOut\":null},{\"tag_id\":5359,\"tag_name\":\"720P\",\"cover\":\"\",\"head_cover\":\"\",\"content\":\"\",\"short_content\":\"\",\"type\":0,\"state\":0,\"ctime\":1436866637,\"count\":{\"view\":0,\"use\":15023,\"atten\":1014},\"is_atten\":0,\"likes\":0,\"hates\":1,\"attribute\":0,\"liked\":0,\"hated\":0,\"showDetail\":false,\"showReport\":false,\"timeOut\":null}],\"comment\":{\"count\":225,\"list\":[\"做了七分钟的字幕……很累的我放弃了\",\"熟肉av10286846（顶上去造福大家）qwq\",\"被骗了无数次眼泪…\"]},\"related\":[{\"aid\":707322,\"cid\":1037250,\"duration\":584,\"pic\":\"http:\\u002F\\u002Fi0.hdslb.com\\u002Fbfs\\u002Farchive\\u002F48e1f2731e7313da1e01cb27a56fb12c1b38acba.jpg\",\"title\":\"【vomic】暗杀教室1-8（2季全）\",\"owner\":{\"name\":\"madaodeath\",\"mid\":332567},\"stat\":{\"danmaku\":2309,\"view\":555610}},{\"aid\":14166918,\"cid\":23125535,\"duration\":214,\"pic\":\"http:\\u002F\\u002Fi0.hdslb.com\\u002Fbfs\\u002Farchive\\u002F26c5ee723aaf5220435d3fa83945c01c19ae7dcf.jpg\",\"title\":\"一部良心漫改电影《暗杀教室》，老师要求学生暗杀自己\",\"owner\":{\"name\":\"一百电影院\",\"mid\":94351240},\"stat\":{\"danmaku\":761,\"view\":168033}},{\"aid\":5290606,\"cid\":8599188,\"duration\":296,\"pic\":\"http:\\u002F\\u002Fi1.hdslb.com\\u002Fbfs\\u002Farchive\\u002F3c6141206ae3f8e535cf49ad4a8b3ec9c63d88c1.jpg\",\"title\":\"暗杀教室\\u002F3年E班 第一季+第二季ED卡合集\",\"owner\":{\"name\":\"茜.C\",\"mid\":529438},\"stat\":{\"danmaku\":5,\"view\":0}},{\"aid\":10286846,\"cid\":17140503,\"duration\":5542,\"pic\":\"http:\\u002F\\u002Fi0.hdslb.com\\u002Fbfs\\u002Farchive\\u002F6ec6dd064eeab972670d9c30cdc342dfe086242d.jpg\",\"title\":\"【剧场版】3年E班 365天的时间【F宅】\",\"owner\":{\"name\":\"空灵雨迹\",\"mid\":223902},\"stat\":{\"danmaku\":45050,\"view\":759875}},{\"aid\":51145409,\"cid\":89540518,\"duration\":1599,\"pic\":\"http:\\u002F\\u002Fi1.hdslb.com\\u002Fbfs\\u002Farchive\\u002Fe05b75f40035e33738eea1d059fadb434eecfa6f.jpg\",\"title\":\"B站评分最低动画！第一季和第二季分差居然如此之大？背后到底有着什么样的故事？\",\"owner\":{\"name\":\"噩梦D\",\"mid\":1816219},\"stat\":{\"danmaku\":5077,\"view\":816999}},{\"aid\":4473501,\"cid\":7249415,\"duration\":459,\"pic\":\"http:\\u002F\\u002Fi0.hdslb.com\\u002Fbfs\\u002Farchive\\u002Fb40e281bd463fae6b44ad26a0702f1ff0c3c39a5.jpg\",\"title\":\"三年E班 第一季NCOP+NCED\",\"owner\":{\"name\":\"羽鸾\",\"mid\":17002887},\"stat\":{\"danmaku\":213,\"view\":147292}},{\"aid\":14548503,\"cid\":23724014,\"duration\":84,\"pic\":\"http:\\u002F\\u002Fi2.hdslb.com\\u002Fbfs\\u002Farchive\\u002F28b536d732c6275222da40fcd05f20184fe59624.jpg\",\"title\":\"【暗杀教室】【真人版】暗杀日常  杀老师滑稽闪现点名CUT\",\"owner\":{\"name\":\"大致若鱼片\",\"mid\":38782648},\"stat\":{\"danmaku\":44,\"view\":17475}},{\"aid\":28546716,\"cid\":49409533,\"duration\":117,\"pic\":\"http:\\u002F\\u002Fi1.hdslb.com\\u002Fbfs\\u002Farchive\\u002Fd84ec9b3beefa3b1bf6ce4c7039afd930456c956.png\",\"title\":\"几十部番剧惨遭下架......\",\"owner\":{\"name\":\"死宅咋啦\",\"mid\":34374640},\"stat\":{\"danmaku\":2460,\"view\":314542}},{\"aid\":7464039,\"cid\":12206604,\"duration\":95,\"pic\":\"http:\\u002F\\u002Fi1.hdslb.com\\u002Fbfs\\u002Farchive\\u002F8c57c80832cff0fff71c012bbcae0fbe7413fe65.jpg\",\"title\":\"【暗杀教室·第三季】片头曲OP 杀老师复活啦~\",\"owner\":{\"name\":\"黄烤鸭\",\"mid\":2553662},\"stat\":{\"danmaku\":92,\"view\":70241}},{\"aid\":12617323,\"cid\":20755041,\"duration\":454,\"pic\":\"http:\\u002F\\u002Fi0.hdslb.com\\u002Fbfs\\u002Farchive\\u002F3866764272d67c6d4dfc5e8de6c780135b54cc6e.png\",\"title\":\"【3年e班Q】  此生无悔入e班，来世愿做他学生，应援全体成员\",\"owner\":{\"name\":\"凤柒懿\",\"mid\":14518050},\"stat\":{\"danmaku\":104,\"view\":25095}},{\"aid\":57709288,\"cid\":100731373,\"duration\":269,\"pic\":\"http:\\u002F\\u002Fi2.hdslb.com\\u002Fbfs\\u002Farchive\\u002F5b1826a2943861c62602e7b93b2c998381c914a5.jpg\",\"title\":\"b站评分9.8的镇站神番，全程高能，却惨遭下架《妄想学生会》\",\"owner\":{\"name\":\"腿毛十九根\",\"mid\":415065990},\"stat\":{\"danmaku\":24,\"view\":36236}},{\"aid\":3533621,\"cid\":5625866,\"duration\":117,\"pic\":\"http:\\u002F\\u002Fi2.hdslb.com\\u002Fbfs\\u002Farchive\\u002F01db62bc6b00965f0988b72a7024ea8e3942e8f6.jpg\",\"title\":\"【1月】极速老师 第二季PV\",\"owner\":{\"name\":\"哔哩哔哩番剧\",\"mid\":928123},\"stat\":{\"danmaku\":1300,\"view\":253510}},{\"aid\":7047487,\"cid\":11490042,\"duration\":735,\"pic\":\"http:\\u002F\\u002Fi2.hdslb.com\\u002Fbfs\\u002Farchive\\u002Fa516003cc3f1e3380d650b2688237b7a71e76cd5.jpg\",\"title\":\"剧场版3年E班 365天的时间 公开前声优特别对谈\",\"owner\":{\"name\":\"雾中的银河\",\"mid\":828489},\"stat\":{\"danmaku\":91,\"view\":8974}},{\"aid\":47442327,\"cid\":83154822,\"duration\":4927,\"pic\":\"http:\\u002F\\u002Fi1.hdslb.com\\u002Fbfs\\u002Farchive\\u002F9bb3fd5e5e5a20b6075040cf3cf95642452552e7.jpg\",\"title\":\"【720P\\u002F剧场版】续·终物语 下【幻之魔都字幕组】\",\"owner\":{\"name\":\"幻之字幕组\",\"mid\":669036},\"stat\":{\"danmaku\":2042,\"view\":125920}},{\"aid\":5012011,\"cid\":8141204,\"duration\":1319,\"pic\":\"http:\\u002F\\u002Fi0.hdslb.com\\u002Fbfs\\u002Farchive\\u002F76fac445721cddd24474ba5b46ede4c6205fc748.jpg\",\"title\":\"C.50【三年E班 第一季】TV＆NC OPxED全合集【OPANDED君】\",\"owner\":{\"name\":\"OPandED君\",\"mid\":4262942},\"stat\":{\"danmaku\":259,\"view\":109863}},{\"aid\":21329925,\"cid\":35065500,\"duration\":1643,\"pic\":\"http:\\u002F\\u002Fi0.hdslb.com\\u002Fbfs\\u002Farchive\\u002Fc8a19d175ab276496c7ec070ce345820cd4f8bf6.jpg\",\"title\":\"那些一出场就满级的动漫主角\",\"owner\":{\"name\":\"十柒号\",\"mid\":7360144},\"stat\":{\"danmaku\":12730,\"view\":1507311}},{\"aid\":9404049,\"cid\":15540428,\"duration\":100,\"pic\":\"http:\\u002F\\u002Fi1.hdslb.com\\u002Fbfs\\u002Farchive\\u002F934052eabcd8c5fcd5973620fa2231bccbee240a.jpg\",\"title\":\"【剧场版】NO GAME NO LIFE ZERO PV 【1080p】\",\"owner\":{\"name\":\"次元中转站\",\"mid\":138645},\"stat\":{\"danmaku\":1233,\"view\":877308}},{\"aid\":20567109,\"cid\":33640298,\"duration\":1906,\"pic\":\"http:\\u002F\\u002Fi2.hdslb.com\\u002Fbfs\\u002Farchive\\u002F942aff9de7a2c9e744a41bb0c88fd0fab16f06d7.png\",\"title\":\"【480P\\u002FDVDrip】3年E班 休学旅行篇【兔子字幕社】\",\"owner\":{\"name\":\"cp999999999\",\"mid\":14429811},\"stat\":{\"danmaku\":41,\"view\":0}},{\"aid\":6948564,\"cid\":11325432,\"duration\":475,\"pic\":\"http:\\u002F\\u002Fi1.hdslb.com\\u002Fbfs\\u002Farchive\\u002F06a07fe3953ab70cec8f39ddadc973ed6e07bf93.jpg\",\"title\":\"暗杀教室真人版CUT\",\"owner\":{\"name\":\"花子だよOvO\",\"mid\":7325656},\"stat\":{\"danmaku\":205,\"view\":46318}},{\"aid\":21230212,\"cid\":34872265,\"duration\":149,\"pic\":\"http:\\u002F\\u002Fi1.hdslb.com\\u002Fbfs\\u002Farchive\\u002Feac13e7ebb8603de48b6b0982b91939aeab9a567.png\",\"title\":\"5部与3年E班相似的动画!\",\"owner\":{\"name\":\"YlessGabriel\",\"mid\":88573087},\"stat\":{\"danmaku\":22,\"view\":10471}},{\"aid\":5140064,\"cid\":8356452,\"duration\":3600,\"pic\":\"http:\\u002F\\u002Fi0.hdslb.com\\u002Fbfs\\u002Farchive\\u002F31b6056ef6d001fd19cf7228c5fb6be01eda1940.jpg\",\"title\":\"【1080P\\u002F剧场版】「头文字D」 Legend3 -梦现-【秋名湖畔】\",\"owner\":{\"name\":\"莉莎娜\",\"mid\":1403138},\"stat\":{\"danmaku\":13245,\"view\":985051}},{\"aid\":7118189,\"cid\":11609661,\"duration\":80,\"pic\":\"http:\\u002F\\u002Fi2.hdslb.com\\u002Fbfs\\u002Farchive\\u002F359fc2404991d0681f4bb25f85b7bbcbb49e1258.jpg\",\"title\":\"【剧场版】暗杀教室：365天的时间 中字预告片\",\"owner\":{\"name\":\"是斐斐不是菲菲\",\"mid\":20021695},\"stat\":{\"danmaku\":48,\"view\":11866}},{\"aid\":6978794,\"cid\":11374639,\"duration\":251,\"pic\":\"http:\\u002F\\u002Fi2.hdslb.com\\u002Fbfs\\u002Farchive\\u002Ff6c72b3152d140e51585750a7bf2d0c8e50c8e07.jpg\",\"title\":\"相遇的时间丨三年E班第二季\",\"owner\":{\"name\":\"莫荼west\",\"mid\":33160974},\"stat\":{\"danmaku\":191,\"view\":0}},{\"aid\":10823259,\"cid\":17856687,\"duration\":380,\"pic\":\"http:\\u002F\\u002Fi2.hdslb.com\\u002Fbfs\\u002Farchive\\u002F5161d918e8d361b6ecfee065e0d087427874d1be.jpg\",\"title\":\"法国短片《迟到的初恋》好甜啊，而且男主又帅又会浪费， 其他视频都是番外吧\",\"owner\":{\"name\":\"紫羽kai\",\"mid\":96842328},\"stat\":{\"danmaku\":899,\"view\":276361}},{\"aid\":64254997,\"cid\":111562719,\"duration\":396,\"pic\":\"http:\\u002F\\u002Fi1.hdslb.com\\u002Fbfs\\u002Farchive\\u002Fde9d1ae0f4311c25972012933559cf04f579dfde.jpg\",\"title\":\"【前方高能】让人百看不厌的动画名场景\",\"owner\":{\"name\":\"LYAnime\",\"mid\":394241986},\"stat\":{\"danmaku\":1930,\"view\":761926}},{\"aid\":10352402,\"cid\":17109706,\"duration\":2261,\"pic\":\"http:\\u002F\\u002Fi1.hdslb.com\\u002Fbfs\\u002Farchive\\u002F1535963169e2fcf9085f9216a1d4f10f90a7d575.jpg\",\"title\":\"365天结束后的时间-业渚part\",\"owner\":{\"name\":\"浅羽柒仔\",\"mid\":15206214},\"stat\":{\"danmaku\":1481,\"view\":56725}},{\"aid\":12542861,\"cid\":20638699,\"duration\":1569,\"pic\":\"http:\\u002F\\u002Fi0.hdslb.com\\u002Fbfs\\u002Farchive\\u002Fa9146c7e5a9408628f9e762d25a2f32be7079dc0.jpg\",\"title\":\"【7月】异世界食堂 04【独家正版】\",\"owner\":{\"name\":\"哔哩哔哩番剧\",\"mid\":928123},\"stat\":{\"danmaku\":102522,\"view\":2659001}},{\"aid\":42995489,\"cid\":75388943,\"duration\":1446,\"pic\":\"http:\\u002F\\u002Fi1.hdslb.com\\u002Fbfs\\u002Farchive\\u002F370b8fd2f6164dee3271af5853bd545ff31addd4.jpg\",\"title\":\"【1月】辉夜大小姐想让我告白~天才们的恋爱头脑战~ 05【独家正版】\",\"owner\":{\"name\":\"哔哩哔哩番剧\",\"mid\":928123},\"stat\":{\"danmaku\":246501,\"view\":9319891}},{\"aid\":21947396,\"cid\":36252362,\"duration\":282,\"pic\":\"http:\\u002F\\u002Fi1.hdslb.com\\u002Fbfs\\u002Farchive\\u002F8ccb17177b02f0a8491b8eb972c3063065359ad3.jpg\",\"title\":\"老外看3年E班杀老师之死的反应（开黑版）\",\"owner\":{\"name\":\"了解一下lll\",\"mid\":313946847},\"stat\":{\"danmaku\":289,\"view\":64901}},{\"aid\":12601325,\"cid\":20730741,\"duration\":744,\"pic\":\"http:\\u002F\\u002Fi1.hdslb.com\\u002Fbfs\\u002Farchive\\u002F6748ef8d40897a3360a9891fd648f39d69fd3cb9.jpg\",\"title\":\"【业渚】暗杀教室应援02-业渚的小剧场\",\"owner\":{\"name\":\"就是个簸箕\",\"mid\":2214743},\"stat\":{\"danmaku\":510,\"view\":27342}},{\"aid\":21523117,\"cid\":38314046,\"duration\":736,\"pic\":\"http:\\u002F\\u002Fi1.hdslb.com\\u002Fbfs\\u002Farchive\\u002Fff1cb3fc395ab5345b7a2eac27977abb854c920d.jpg\",\"title\":\"【1080P+\\u002FBD】3年E班 第二季 - OP\\u002FED (有字幕+无字幕)\",\"owner\":{\"name\":\"玩1314\",\"mid\":13721927},\"stat\":{\"danmaku\":3,\"view\":2350}},{\"aid\":19072638,\"cid\":31113117,\"duration\":191,\"pic\":\"http:\\u002F\\u002Fi2.hdslb.com\\u002Fbfs\\u002Farchive\\u002Fca100b1e8d03222ca5a92ee239d26562c98c4f17.jpg\",\"title\":\"【七人传奇第一季】七罪之魂\",\"owner\":{\"name\":\"Toams菊猴\",\"mid\":33140739},\"stat\":{\"danmaku\":34,\"view\":165180}},{\"aid\":21945102,\"cid\":36247974,\"duration\":643,\"pic\":\"http:\\u002F\\u002Fi0.hdslb.com\\u002Fbfs\\u002Farchive\\u002F3f726f950c6e26bffd4c899c6c06b8d0a096e337.png\",\"title\":\"十大主角对任何人都是碾压的装逼番（类似Overlord）\",\"owner\":{\"name\":\"可爱の一狗\",\"mid\":15155926},\"stat\":{\"danmaku\":1005,\"view\":387977}},{\"aid\":17319556,\"cid\":28297790,\"duration\":619,\"pic\":\"http:\\u002F\\u002Fi0.hdslb.com\\u002Fbfs\\u002Farchive\\u002F28971f9c07de08a0ded07e38e59d74c55103202c.jpg\",\"title\":\"Top 10 十大集体装逼\\u002F开大的豪华场景\",\"owner\":{\"name\":\"三爷的口嚼酒\",\"mid\":13458711},\"stat\":{\"danmaku\":25704,\"view\":5718082}},{\"aid\":25892696,\"cid\":44280294,\"duration\":756,\"pic\":\"http:\\u002F\\u002Fi1.hdslb.com\\u002Fbfs\\u002Farchive\\u002Fb282d02532ceb037447347f0eedf74b6521488a7.jpg\",\"title\":\"【1月】卫宫家今天的饭 07【独家正版】\",\"owner\":{\"name\":\"哔哩哔哩番剧\",\"mid\":928123},\"stat\":{\"danmaku\":64154,\"view\":3245077}},{\"aid\":11798196,\"cid\":19482320,\"duration\":1431,\"pic\":\"http:\\u002F\\u002Fi2.hdslb.com\\u002Fbfs\\u002Farchive\\u002F51ed594dfa854a4741029d95eb6bd335dfbecb1d.jpg\",\"title\":\"【7月】Fate\\u002FApocrypha 01【独家正版】\",\"owner\":{\"name\":\"哔哩哔哩番剧\",\"mid\":928123},\"stat\":{\"danmaku\":342272,\"view\":15809340}},{\"aid\":2914585,\"cid\":4557754,\"duration\":5280,\"pic\":\"http:\\u002F\\u002Fi0.hdslb.com\\u002Fbfs\\u002Farchive\\u002Fa9a1e2a8da7c9101861587f38fd7b2a8e271a677.jpg\",\"title\":\"【剧场版】排球少年「结束与开始」【720P】\",\"owner\":{\"name\":\"一条鱼鱼鱼阿\",\"mid\":9104680},\"stat\":{\"danmaku\":4786,\"view\":206081}},{\"aid\":13974852,\"cid\":22826841,\"duration\":150,\"pic\":\"http:\\u002F\\u002Fi2.hdslb.com\\u002Fbfs\\u002Farchive\\u002Ff6708409795219c97c30e22bd628a75a4452881a.jpg\",\"title\":\"【三年E班】另一个结局【教师节快乐】\",\"owner\":{\"name\":\"白衣香木\",\"mid\":10314048},\"stat\":{\"danmaku\":97,\"view\":19312}},{\"aid\":63521916,\"cid\":110306461,\"duration\":419,\"pic\":\"http:\\u002F\\u002Fi0.hdslb.com\\u002Fbfs\\u002Farchive\\u002Fc25fc20d870ce1624b07d9f56cb19808711144d9.jpg\",\"title\":\"动漫推荐～十部开局无敌，主角龙傲天动漫\",\"owner\":{\"name\":\"烽叶三三\",\"mid\":21262420},\"stat\":{\"danmaku\":231,\"view\":41433}},{\"aid\":51884888,\"cid\":90834884,\"duration\":640,\"pic\":\"http:\\u002F\\u002Fi0.hdslb.com\\u002Fbfs\\u002Farchive\\u002F839722bb2ecf5bcfcb6dbf3215aab634de8c13ef.jpg\",\"title\":\"十大动画，主角是一个转学生！\",\"owner\":{\"name\":\"千代语默\",\"mid\":189104868},\"stat\":{\"danmaku\":314,\"view\":164490}}],\"isClient\":false,\"error\":{},\"player\":\"\",\"playurl\":{},\"user\":{},\"cidMap\":{},\"insertScripts\":[\"\\u002F\\u002Fs1.hdslb.com\\u002Fbfs\\u002Fstatic\\u002Fjinkela\\u002Fvideo\\u002Fstardust-video.532e11807db0ff6f4161f5d43bc9d45bdb5ad2b9.js\"]};(function(){var s;(s=document.currentScript||document.scripts[document.scripts.length-1]).parentNode.removeChild(s);}());</script> <link rel=\"stylesheet\" href=\"//s1.hdslb.com/bfs/static/jinkela/video/css/stardust-video.0.532e11807db0ff6f4161f5d43bc9d45bdb5ad2b9.css\"></head><body><script type=\"text/javascript\">function getIEVersion(){var e=99;if(\"Microsoft Internet Explorer\"==navigator.appName){var t=navigator.userAgent;null!=new RegExp(\"MSIE ([0-9]{1,}[.0-9]{0,})\").exec(t)&&(e=parseFloat(RegExp.$1))}return e}function setSize(){var e=window.isWide,t=350,i=document.body.offsetHeight,o=document.body.offsetWidth,n=parseInt(16*(.743*i-108.7)/9),d=o-152-t,r=d<n?d:n;r<638&&(r=638),1280<r&&(r=1280);var s,l=r+t;s=window.hasBlackSide&&!window.isWide?Math.round((r-14+(e?t:0))*(9/16)+46)+96:Math.round((r+(e?t:0))*(9/16))+46;var a=\"0 \"+(o<l+152?76:0),c=document.querySelector(\".v-wrap\"),u=document.querySelector(\".l-con\"),w=document.querySelector(\"#bofqi\"),y=document.querySelector(\"#danmukuBox\"),p=document.querySelector(\"#playerWrap\");c&&(c.style.width=l+\"px\",c.style.padding=a+\"px\"),w&&(w.style.width=l-(e?0:t)+\"px\",w.style.height=s+\"px\"),u&&(u.style.width=l-t+\"px\"),e?(y&&(y.style.height=s-0+\"px\"),p&&(p.style.height=s-0+\"px\"),w&&(w.style.position=\"relative\")):(y&&(y.style.height=\"auto\"),p&&(p.style.height=\"auto\"),w&&(w.style.position=\"static\"))}getIEVersion()<=9&&(document.body.innerHTML=\"<div class='ie-fix'><div class='title'>为了保障你的账号安全和最佳预览体验，播放页已不支持IE9及以下IE版本浏览器访问，建议你使用Chrome等高级浏览器或升级到IE最新版本浏览器。</div></div>\"),window.addEventListener(\"resize\",function(){setSize()}),window.PlayerAgent={player_widewin:function(){window.scrollTo(0,55),window.isWide=!0,setSize()},player_fullwin:function(e){window.scrollTo(0,0),window.isWide=!1,setSize()},toggleBlackSide:function(e){window.hasBlackSide=e,setSize()}}</script><script type=\"text/javascript\" src=\"//s1.hdslb.com/bfs/static/player/main/video.js?v=20190909\"></script><div class=\"z-top-container has-stardust\" style=\"height:50px;box-shadow:0 1px 2px rgba(0,0,0,.1)\"></div><div id=\"video-page-app\"></div><!-- built files will be auto injected --><div id=\"app\" data-server-rendered=\"true\"><div class=\"v-wrap\"><div class=\"l-con\"><div id=\"viewbox_report\" class=\"video-info report-wrap-module report-scroll-module\"><h1 title=\"【剧场版】3年E班剧场版 365天的时间【生肉/720P】\" class=\"video-title\"><!----><span class=\"tit tr-fix\">【剧场版】3年E班剧场版 365天的时间【生肉/720P】</span></h1><div class=\"video-data\"><span class=\"a-crumbs\"><a target=\"_blank\" href=\"//www.bilibili.com/anime/\">番剧</a><i class=\"van-icon-general_enter_s\"></i><a target=\"_blank\" href=\"//www.bilibili.com/v/anime/serial/\">连载动画</a></span><span>2017-05-03 13:29:50</span><!----></div><div class=\"video-data\"><span title=\"总播放数--\" class=\"view\">--播放 · </span><span title=\"历史累计弹幕数--\" class=\"dm\">--弹幕</span><!----><!----></div></div><div id=\"playerWrap\" class=\"player-wrap\"><div id=\"bofqi\"></div><div><script type=\"text/javascript\">\n        setSize()\n\n        function gqs(name) {\n          var reg = new RegExp(\"(^|&)\" + name + \"=([^&]*)(&|$)\");\n          var r = window.location.search.substr(1).match(reg);\n          if (r != null) {\n            return unescape(r[2])\n          }\n          return null\n        }\n\n        function getCookie(name) { \n          var reg = new RegExp(\"(^| )\"+name+\"=([^;]*)(;|$)\")\n          var r = document.cookie.match(reg)\n          return r ? unescape(r[2]) : null\n        } \n\n        var vd = window.__INITIAL_STATE__ && window.__INITIAL_STATE__.videoData\n        if(vd && vd.aid) {\n          if(vd.embedPlayer) {\n            var fp = gqs('p') || gqs('page') || null\n            var p = fp ? fp - 1 : 0\n            var player = {\n              aid: vd.aid,\n              cid: (vd.pages[p] && vd.pages[p].cid) || vd.pages[0].cid,\n              attribute: vd.attribute\n            }\n            EmbedPlayer(\"player\", \"//static.hdslb.com/play.swf\", \"cid=\" + player.cid + \"&aid=\" + player.aid + \"&attribute=\" + player.attribute)\n          }else if(vd.embed) {\n            document.querySelector(\"#bofqi\").innerHTML = vd.embed\n          }\n        }\n      </script></div></div><div id=\"arc_toolbar_report\" class=\"video-toolbar report-wrap-module report-scroll-module\"><div class=\"ops\"><span title=\"点赞数0\" class=\"like\"><!----><!----><!----><!----><!----><i class=\"van-icon-videodetails_like\" style=\"color:;\"></i>--\n    </span><span title=\"投硬币枚数\" class=\"coin\"><canvas width=\"34\" height=\"34\" class=\"ring-progress\" style=\"width:34px;height:34px;left:-3px;top:-3px;\"></canvas><!----><i class=\"van-icon-videodetails_throw\" style=\"color:;\"></i>\n      --\n    </span><span title=\"收藏人数\" class=\"collect\"><canvas width=\"34\" height=\"34\" class=\"ring-progress\" style=\"width:34px;height:34px;left:-3px;top:-3px;\"></canvas><!----><i class=\"van-icon-videodetails_collec\" style=\"color:;\"></i>--\n    </span><span title=\"分享\" class=\"share\"><i class=\"van-icon-videodetails_share\"></i>--\n      <!----></span></div><div class=\"more\"><i class=\"van-icon-general_moreactions\"></i><!----></div><div class=\"appeal-text\">稿件投诉</div></div><div id=\"v_desc\" class=\"video-desc report-wrap-module report-scroll-module\"><div class=\"info open\">http://盘.baidu.com/s/1i4PiUKd 密码：7inh\n召唤字幕菌字幕组\n感谢贴吧吧友</div><!----><!----></div><div id=\"v_tag\" class=\"s_tag report-wrap-module report-scroll-module\"><ul class=\"tag-area clearfix\"><li class=\"tag\"><a href=\"//search.bilibili.com/all?keyword=%E5%89%A7%E5%9C%BA%E7%89%88&amp;from_source=video_tag\" target=\"_blank\">剧场版</a><!----><!----></li><li class=\"tag\"><a href=\"//search.bilibili.com/all?keyword=%E6%97%A5%E6%9C%AC%E5%8A%A8%E7%94%BB&amp;from_source=video_tag\" target=\"_blank\">日本动画</a><!----><!----></li><li class=\"tag\"><a href=\"//search.bilibili.com/all?keyword=3%E5%B9%B4E%E7%8F%AD&amp;from_source=video_tag\" target=\"_blank\">3年E班</a><!----><!----></li><li class=\"tag\"><a href=\"//search.bilibili.com/all?keyword=%E7%A6%8F%E5%B1%B1%E6%B6%A6&amp;from_source=video_tag\" target=\"_blank\">福山润</a><!----><!----></li><li class=\"tag\"><a href=\"//search.bilibili.com/all?keyword=720P&amp;from_source=video_tag\" target=\"_blank\">720P</a><!----><!----></li><!----><a class=\"btn-add\"><span class=\"one\"></span><span class=\"two\"></span></a><!----></ul></div><!----><div id=\"comment\" class=\"comment-m report-wrap-module report-scroll-module\"><div class=\"common\"><div class=\"b-head\"><span class=\"b-head-t results\"></span><span class=\"b-head-t\">评论</span></div><div class=\"comment\"></div></div></div></div><div class=\"r-con\"><div id=\"v_upinfo\" class=\"up-info report-wrap-module report-scroll-module\"><div class=\"u-face\"><a href=\"//space.bilibili.com/5977857\" target=\"_blank\" report-id=\"head\" class=\"fa\"><!----><!----><!----><!----></a></div><div class=\"u-info\"><div class=\"name\" style=\"line-height:20px;height:20px;\"><a href=\"//space.bilibili.com/5977857\" target=\"_blank\" report-id=\"name\" class=\"username is-vip\">躲在树上吃翔</a><a href=\"//message.bilibili.com/#whisper/mid5977857\" target=\"_blank\" class=\"message\"><i class=\"van-icon-videodetails_messag\"></i>发消息</a></div><div title=\"我还是支持拜仁慕尼黑\" class=\"desc\">\n      我还是支持拜仁慕尼黑\n    </div></div><div class=\"btn-panel\"><!----><div class=\"default-btn follow-btn b-gz not-follow\"><span><i class=\"van-icon-general_addto_s\"></i>关注 <span>462</span></span><!----><!----></div></div></div><div id=\"danmukuBox\" class=\"danmaku-box\"><div class=\"danmaku-wrap\"></div></div><!----><div id=\"slide_ad\" class=\"report-wrap-module report-scroll-module\"></div><div id=\"reco_list\" class=\"recommend-list report-wrap-module report-scroll-module\"><div class=\"rec-title\">\n    相关推荐\n\n    </div><div class=\"rec-list\"><!----><!----><!----><div class=\"video-page-card\"><div class=\"card-box\"><div class=\"pic-box\"><div class=\"pic\"><a href=\"/video/av707322/?spm_id_from=333.788.videocard.0\"><img src=\"\" alt=\"【vomic】暗杀教室1-8（2季全）\" width=\"168\" height=\"95\"></a><span class=\"mask-video\"></span><span class=\"duration\">09:44</span></div><div class=\"watch-later-video van-watchlater\"><span class=\"wl-tips\" style=\"display:none;\"></span></div></div><div class=\"info\"><a href=\"/video/av707322/?spm_id_from=333.788.videocard.0\" title=\"【vomic】暗杀教室1-8（2季全）\" class=\"title\">【vomic】暗杀教室1-8（2季全）</a><div class=\"count up\"><a href=\"//space.bilibili.com/332567/\" target=\"_blank\">madaodeath</a></div><div class=\"count\">\n        55.6万播放 · 2309弹幕\n      </div></div></div></div><div class=\"video-page-card\"><div class=\"card-box\"><div class=\"pic-box\"><div class=\"pic\"><a href=\"/video/av14166918/?spm_id_from=333.788.videocard.1\"><img src=\"\" alt=\"一部良心漫改电影《暗杀教室》，老师要求学生暗杀自己\" width=\"168\" height=\"95\"></a><span class=\"mask-video\"></span><span class=\"duration\">03:34</span></div><div class=\"watch-later-video van-watchlater\"><span class=\"wl-tips\" style=\"display:none;\"></span></div></div><div class=\"info\"><a href=\"/video/av14166918/?spm_id_from=333.788.videocard.1\" title=\"一部良心漫改电影《暗杀教室》，老师要求学生暗杀自己\" class=\"title\">一部良心漫改电影《暗杀教室》，老师要求学生暗杀自己</a><div class=\"count up\"><a href=\"//space.bilibili.com/94351240/\" target=\"_blank\">一百电影院</a></div><div class=\"count\">\n        16.8万播放 · 761弹幕\n      </div></div></div></div><div class=\"video-page-card\"><div class=\"card-box\"><div class=\"pic-box\"><div class=\"pic\"><a href=\"/video/av5290606/?spm_id_from=333.788.videocard.2\"><img src=\"\" alt=\"暗杀教室/3年E班 第一季+第二季ED卡合集\" width=\"168\" height=\"95\"></a><span class=\"mask-video\"></span><span class=\"duration\">04:56</span></div><div class=\"watch-later-video van-watchlater\"><span class=\"wl-tips\" style=\"display:none;\"></span></div></div><div class=\"info\"><a href=\"/video/av5290606/?spm_id_from=333.788.videocard.2\" title=\"暗杀教室/3年E班 第一季+第二季ED卡合集\" class=\"title\">暗杀教室/3年E班 第一季+第二季ED卡合集</a><div class=\"count up\"><a href=\"//space.bilibili.com/529438/\" target=\"_blank\">茜.C</a></div><div class=\"count\">\n        0播放 · 5弹幕\n      </div></div></div></div><div class=\"video-page-card\"><div class=\"card-box\"><div class=\"pic-box\"><div class=\"pic\"><a href=\"/video/av10286846/?spm_id_from=333.788.videocard.3\"><img src=\"\" alt=\"【剧场版】3年E班 365天的时间【F宅】\" width=\"168\" height=\"95\"></a><span class=\"mask-video\"></span><span class=\"duration\">1:32:22</span></div><div class=\"watch-later-video van-watchlater\"><span class=\"wl-tips\" style=\"display:none;\"></span></div></div><div class=\"info\"><a href=\"/video/av10286846/?spm_id_from=333.788.videocard.3\" title=\"【剧场版】3年E班 365天的时间【F宅】\" class=\"title\">【剧场版】3年E班 365天的时间【F宅】</a><div class=\"count up\"><a href=\"//space.bilibili.com/223902/\" target=\"_blank\">空灵雨迹</a></div><div class=\"count\">\n        76.0万播放 · 4.5万弹幕\n      </div></div></div></div><div class=\"video-page-card\"><div class=\"card-box\"><div class=\"pic-box\"><div class=\"pic\"><a href=\"/video/av51145409/?spm_id_from=333.788.videocard.4\"><img src=\"\" alt=\"B站评分最低动画！第一季和第二季分差居然如此之大？背后到底有着什么样的故事？\" width=\"168\" height=\"95\"></a><span class=\"mask-video\"></span><span class=\"duration\">26:39</span></div><div class=\"watch-later-video van-watchlater\"><span class=\"wl-tips\" style=\"display:none;\"></span></div></div><div class=\"info\"><a href=\"/video/av51145409/?spm_id_from=333.788.videocard.4\" title=\"B站评分最低动画！第一季和第二季分差居然如此之大？背后到底有着什么样的故事？\" class=\"title\">B站评分最低动画！第一季和第二季分差居然如此之大？背后到底有着什么样的故事？</a><div class=\"count up\"><a href=\"//space.bilibili.com/1816219/\" target=\"_blank\">噩梦D</a></div><div class=\"count\">\n        81.7万播放 · 5077弹幕\n      </div></div></div></div><div class=\"video-page-card\"><div class=\"card-box\"><div class=\"pic-box\"><div class=\"pic\"><a href=\"/video/av4473501/?spm_id_from=333.788.videocard.5\"><img src=\"\" alt=\"三年E班 第一季NCOP+NCED\" width=\"168\" height=\"95\"></a><span class=\"mask-video\"></span><span class=\"duration\">07:39</span></div><div class=\"watch-later-video van-watchlater\"><span class=\"wl-tips\" style=\"display:none;\"></span></div></div><div class=\"info\"><a href=\"/video/av4473501/?spm_id_from=333.788.videocard.5\" title=\"三年E班 第一季NCOP+NCED\" class=\"title\">三年E班 第一季NCOP+NCED</a><div class=\"count up\"><a href=\"//space.bilibili.com/17002887/\" target=\"_blank\">羽鸾</a></div><div class=\"count\">\n        14.7万播放 · 213弹幕\n      </div></div></div></div><div class=\"video-page-card\"><div class=\"card-box\"><div class=\"pic-box\"><div class=\"pic\"><a href=\"/video/av14548503/?spm_id_from=333.788.videocard.6\"><img src=\"\" alt=\"【暗杀教室】【真人版】暗杀日常  杀老师滑稽闪现点名CUT\" width=\"168\" height=\"95\"></a><span class=\"mask-video\"></span><span class=\"duration\">01:24</span></div><div class=\"watch-later-video van-watchlater\"><span class=\"wl-tips\" style=\"display:none;\"></span></div></div><div class=\"info\"><a href=\"/video/av14548503/?spm_id_from=333.788.videocard.6\" title=\"【暗杀教室】【真人版】暗杀日常  杀老师滑稽闪现点名CUT\" class=\"title\">【暗杀教室】【真人版】暗杀日常  杀老师滑稽闪现点名CUT</a><div class=\"count up\"><a href=\"//space.bilibili.com/38782648/\" target=\"_blank\">大致若鱼片</a></div><div class=\"count\">\n        1.7万播放 · 44弹幕\n      </div></div></div></div><div class=\"video-page-card\"><div class=\"card-box\"><div class=\"pic-box\"><div class=\"pic\"><a href=\"/video/av28546716/?spm_id_from=333.788.videocard.7\"><img src=\"\" alt=\"几十部番剧惨遭下架......\" width=\"168\" height=\"95\"></a><span class=\"mask-video\"></span><span class=\"duration\">01:57</span></div><div class=\"watch-later-video van-watchlater\"><span class=\"wl-tips\" style=\"display:none;\"></span></div></div><div class=\"info\"><a href=\"/video/av28546716/?spm_id_from=333.788.videocard.7\" title=\"几十部番剧惨遭下架......\" class=\"title\">几十部番剧惨遭下架......</a><div class=\"count up\"><a href=\"//space.bilibili.com/34374640/\" target=\"_blank\">死宅咋啦</a></div><div class=\"count\">\n        31.5万播放 · 2460弹幕\n      </div></div></div></div><div class=\"video-page-card\"><div class=\"card-box\"><div class=\"pic-box\"><div class=\"pic\"><a href=\"/video/av7464039/?spm_id_from=333.788.videocard.8\"><img src=\"\" alt=\"【暗杀教室·第三季】片头曲OP 杀老师复活啦~\" width=\"168\" height=\"95\"></a><span class=\"mask-video\"></span><span class=\"duration\">01:35</span></div><div class=\"watch-later-video van-watchlater\"><span class=\"wl-tips\" style=\"display:none;\"></span></div></div><div class=\"info\"><a href=\"/video/av7464039/?spm_id_from=333.788.videocard.8\" title=\"【暗杀教室·第三季】片头曲OP 杀老师复活啦~\" class=\"title\">【暗杀教室·第三季】片头曲OP 杀老师复活啦~</a><div class=\"count up\"><a href=\"//space.bilibili.com/2553662/\" target=\"_blank\">黄烤鸭</a></div><div class=\"count\">\n        7.0万播放 · 92弹幕\n      </div></div></div></div><div class=\"video-page-card\"><div class=\"card-box\"><div class=\"pic-box\"><div class=\"pic\"><a href=\"/video/av12617323/?spm_id_from=333.788.videocard.9\"><img src=\"\" alt=\"【3年e班Q】  此生无悔入e班，来世愿做他学生，应援全体成员\" width=\"168\" height=\"95\"></a><span class=\"mask-video\"></span><span class=\"duration\">07:34</span></div><div class=\"watch-later-video van-watchlater\"><span class=\"wl-tips\" style=\"display:none;\"></span></div></div><div class=\"info\"><a href=\"/video/av12617323/?spm_id_from=333.788.videocard.9\" title=\"【3年e班Q】  此生无悔入e班，来世愿做他学生，应援全体成员\" class=\"title\">【3年e班Q】  此生无悔入e班，来世愿做他学生，应援全体成员</a><div class=\"count up\"><a href=\"//space.bilibili.com/14518050/\" target=\"_blank\">凤柒懿</a></div><div class=\"count\">\n        2.5万播放 · 104弹幕\n      </div></div></div></div><div class=\"video-page-card\"><div class=\"card-box\"><div class=\"pic-box\"><div class=\"pic\"><a href=\"/video/av57709288/?spm_id_from=333.788.videocard.10\"><img src=\"\" alt=\"b站评分9.8的镇站神番，全程高能，却惨遭下架《妄想学生会》\" width=\"168\" height=\"95\"></a><span class=\"mask-video\"></span><span class=\"duration\">04:29</span></div><div class=\"watch-later-video van-watchlater\"><span class=\"wl-tips\" style=\"display:none;\"></span></div></div><div class=\"info\"><a href=\"/video/av57709288/?spm_id_from=333.788.videocard.10\" title=\"b站评分9.8的镇站神番，全程高能，却惨遭下架《妄想学生会》\" class=\"title\">b站评分9.8的镇站神番，全程高能，却惨遭下架《妄想学生会》</a><div class=\"count up\"><a href=\"//space.bilibili.com/415065990/\" target=\"_blank\">腿毛十九根</a></div><div class=\"count\">\n        3.6万播放 · 24弹幕\n      </div></div></div></div><div class=\"video-page-card\"><div class=\"card-box\"><div class=\"pic-box\"><div class=\"pic\"><a href=\"/video/av3533621/?spm_id_from=333.788.videocard.11\"><img src=\"\" alt=\"【1月】极速老师 第二季PV\" width=\"168\" height=\"95\"></a><span class=\"mask-video\"></span><span class=\"duration\">01:57</span></div><div class=\"watch-later-video van-watchlater\"><span class=\"wl-tips\" style=\"display:none;\"></span></div></div><div class=\"info\"><a href=\"/video/av3533621/?spm_id_from=333.788.videocard.11\" title=\"【1月】极速老师 第二季PV\" class=\"title\">【1月】极速老师 第二季PV</a><div class=\"count up\"><a href=\"//space.bilibili.com/928123/\" target=\"_blank\">哔哩哔哩番剧</a></div><div class=\"count\">\n        25.4万播放 · 1300弹幕\n      </div></div></div></div><div class=\"video-page-card\"><div class=\"card-box\"><div class=\"pic-box\"><div class=\"pic\"><a href=\"/video/av7047487/?spm_id_from=333.788.videocard.12\"><img src=\"\" alt=\"剧场版3年E班 365天的时间 公开前声优特别对谈\" width=\"168\" height=\"95\"></a><span class=\"mask-video\"></span><span class=\"duration\">12:15</span></div><div class=\"watch-later-video van-watchlater\"><span class=\"wl-tips\" style=\"display:none;\"></span></div></div><div class=\"info\"><a href=\"/video/av7047487/?spm_id_from=333.788.videocard.12\" title=\"剧场版3年E班 365天的时间 公开前声优特别对谈\" class=\"title\">剧场版3年E班 365天的时间 公开前声优特别对谈</a><div class=\"count up\"><a href=\"//space.bilibili.com/828489/\" target=\"_blank\">雾中的银河</a></div><div class=\"count\">\n        8974播放 · 91弹幕\n      </div></div></div></div><div class=\"video-page-card\"><div class=\"card-box\"><div class=\"pic-box\"><div class=\"pic\"><a href=\"/video/av47442327/?spm_id_from=333.788.videocard.13\"><img src=\"\" alt=\"【720P/剧场版】续·终物语 下【幻之魔都字幕组】\" width=\"168\" height=\"95\"></a><span class=\"mask-video\"></span><span class=\"duration\">1:22:07</span></div><div class=\"watch-later-video van-watchlater\"><span class=\"wl-tips\" style=\"display:none;\"></span></div></div><div class=\"info\"><a href=\"/video/av47442327/?spm_id_from=333.788.videocard.13\" title=\"【720P/剧场版】续·终物语 下【幻之魔都字幕组】\" class=\"title\">【720P/剧场版】续·终物语 下【幻之魔都字幕组】</a><div class=\"count up\"><a href=\"//space.bilibili.com/669036/\" target=\"_blank\">幻之字幕组</a></div><div class=\"count\">\n        12.6万播放 · 2042弹幕\n      </div></div></div></div><div class=\"video-page-card\"><div class=\"card-box\"><div class=\"pic-box\"><div class=\"pic\"><a href=\"/video/av5012011/?spm_id_from=333.788.videocard.14\"><img src=\"\" alt=\"C.50【三年E班 第一季】TV＆NC OPxED全合集【OPANDED君】\" width=\"168\" height=\"95\"></a><span class=\"mask-video\"></span><span class=\"duration\">21:59</span></div><div class=\"watch-later-video van-watchlater\"><span class=\"wl-tips\" style=\"display:none;\"></span></div></div><div class=\"info\"><a href=\"/video/av5012011/?spm_id_from=333.788.videocard.14\" title=\"C.50【三年E班 第一季】TV＆NC OPxED全合集【OPANDED君】\" class=\"title\">C.50【三年E班 第一季】TV＆NC OPxED全合集【OPANDED君】</a><div class=\"count up\"><a href=\"//space.bilibili.com/4262942/\" target=\"_blank\">OPandED君</a></div><div class=\"count\">\n        11.0万播放 · 259弹幕\n      </div></div></div></div><div class=\"video-page-card\"><div class=\"card-box\"><div class=\"pic-box\"><div class=\"pic\"><a href=\"/video/av21329925/?spm_id_from=333.788.videocard.15\"><img src=\"\" alt=\"那些一出场就满级的动漫主角\" width=\"168\" height=\"95\"></a><span class=\"mask-video\"></span><span class=\"duration\">27:23</span></div><div class=\"watch-later-video van-watchlater\"><span class=\"wl-tips\" style=\"display:none;\"></span></div></div><div class=\"info\"><a href=\"/video/av21329925/?spm_id_from=333.788.videocard.15\" title=\"那些一出场就满级的动漫主角\" class=\"title\">那些一出场就满级的动漫主角</a><div class=\"count up\"><a href=\"//space.bilibili.com/7360144/\" target=\"_blank\">十柒号</a></div><div class=\"count\">\n        150.7万播放 · 1.3万弹幕\n      </div></div></div></div><div class=\"video-page-card\"><div class=\"card-box\"><div class=\"pic-box\"><div class=\"pic\"><a href=\"/video/av9404049/?spm_id_from=333.788.videocard.16\"><img src=\"\" alt=\"【剧场版】NO GAME NO LIFE ZERO PV 【1080p】\" width=\"168\" height=\"95\"></a><span class=\"mask-video\"></span><span class=\"duration\">01:40</span></div><div class=\"watch-later-video van-watchlater\"><span class=\"wl-tips\" style=\"display:none;\"></span></div></div><div class=\"info\"><a href=\"/video/av9404049/?spm_id_from=333.788.videocard.16\" title=\"【剧场版】NO GAME NO LIFE ZERO PV 【1080p】\" class=\"title\">【剧场版】NO GAME NO LIFE ZERO PV 【1080p】</a><div class=\"count up\"><a href=\"//space.bilibili.com/138645/\" target=\"_blank\">次元中转站</a></div><div class=\"count\">\n        87.7万播放 · 1233弹幕\n      </div></div></div></div><div class=\"video-page-card\"><div class=\"card-box\"><div class=\"pic-box\"><div class=\"pic\"><a href=\"/video/av20567109/?spm_id_from=333.788.videocard.17\"><img src=\"\" alt=\"【480P/DVDrip】3年E班 休学旅行篇【兔子字幕社】\" width=\"168\" height=\"95\"></a><span class=\"mask-video\"></span><span class=\"duration\">31:46</span></div><div class=\"watch-later-video van-watchlater\"><span class=\"wl-tips\" style=\"display:none;\"></span></div></div><div class=\"info\"><a href=\"/video/av20567109/?spm_id_from=333.788.videocard.17\" title=\"【480P/DVDrip】3年E班 休学旅行篇【兔子字幕社】\" class=\"title\">【480P/DVDrip】3年E班 休学旅行篇【兔子字幕社】</a><div class=\"count up\"><a href=\"//space.bilibili.com/14429811/\" target=\"_blank\">cp999999999</a></div><div class=\"count\">\n        0播放 · 41弹幕\n      </div></div></div></div><div class=\"video-page-card\"><div class=\"card-box\"><div class=\"pic-box\"><div class=\"pic\"><a href=\"/video/av6948564/?spm_id_from=333.788.videocard.18\"><img src=\"\" alt=\"暗杀教室真人版CUT\" width=\"168\" height=\"95\"></a><span class=\"mask-video\"></span><span class=\"duration\">07:55</span></div><div class=\"watch-later-video van-watchlater\"><span class=\"wl-tips\" style=\"display:none;\"></span></div></div><div class=\"info\"><a href=\"/video/av6948564/?spm_id_from=333.788.videocard.18\" title=\"暗杀教室真人版CUT\" class=\"title\">暗杀教室真人版CUT</a><div class=\"count up\"><a href=\"//space.bilibili.com/7325656/\" target=\"_blank\">花子だよOvO</a></div><div class=\"count\">\n        4.6万播放 · 205弹幕\n      </div></div></div></div><div class=\"video-page-card\"><div class=\"card-box\"><div class=\"pic-box\"><div class=\"pic\"><a href=\"/video/av21230212/?spm_id_from=333.788.videocard.19\"><img src=\"\" alt=\"5部与3年E班相似的动画!\" width=\"168\" height=\"95\"></a><span class=\"mask-video\"></span><span class=\"duration\">02:29</span></div><div class=\"watch-later-video van-watchlater\"><span class=\"wl-tips\" style=\"display:none;\"></span></div></div><div class=\"info\"><a href=\"/video/av21230212/?spm_id_from=333.788.videocard.19\" title=\"5部与3年E班相似的动画!\" class=\"title\">5部与3年E班相似的动画!</a><div class=\"count up\"><a href=\"//space.bilibili.com/88573087/\" target=\"_blank\">YlessGabriel</a></div><div class=\"count\">\n        1.0万播放 · 22弹幕\n      </div></div></div></div></div><div class=\"rec-footer\" style=\"display:;\">展开</div></div><!----><!----></div><!----><!----><!----><div class=\"float-nav\" style=\"display:none;\"><div class=\"nav-menu\"><div title=\"返回顶部\" class=\"item backup\"><i class=\"van-icon-general_pullup_s\"></i></div><div title=\"点击打开迷你播放器\" class=\"item mini\"><span>mini</span><span>OFF</span></div><a href=\"//www.bilibili.com/blackboard/help.html#%E5%B8%B8%E8%A7%81%E6%92%AD%E6%94%BE%E9%97%AE%E9%A2%98%E8%87%AA%E6%95%91%E6%96%B9%E6%B3%95\" target=\"_blank\" title=\"帮助反馈\"><div class=\"item help\"><i class=\"van-icon-floatwindow_custome\"></i></div></a></div></div><div id=\"entryOld\" class=\"guide report-wrap-module report-scroll-module\"><div class=\"feedback-btn\"><!----><a href=\"//www.bilibili.com/blackboard/activity-XDTj0LNChQ.html\" target=\"_blank\">试用<br>反馈</a></div><div class=\"old-btn\"><a>返回<br>旧版</a></div></div><div class=\"interact-dialog\" style=\"display:none;\"><div class=\"bg\"></div><div class=\"con\"><img src=\"//s1.hdslb.com/bfs/static/jinkela/video/asserts/interact-dialog.png\" class=\"pic\"><span class=\"btn\"></span></div></div></div></div><script type=\"text/javascript\" src=\"//s1.hdslb.com/bfs/seed/log/report/log-reporter.js\" crossorigin></script><script type=\"text/javascript\">var jq_url=\"//s1.hdslb.com/bfs/static/jinkela/long/js/jquery/jquery1.7.2.min.js\",header_url=\"//s1.hdslb.com/bfs/seed/jinkela/header/header.js\",comment_url=\"//static.hdslb.com/phoenix/dist/js/comment.min.js\",ad_url=\"//s1.hdslb.com/bfs/cm/st/bundle.js\",comment_css_url=\"//static.hdslb.com/phoenix/dist/css/comment.min.css\";function loadScript(e,i){var t=document.createElement(\"script\");t.type=\"text/javascript\",t.src=e,document.body.appendChild(t),t.onload=function(){i&&i()}}function loadLink(e){var i=document.createElement(\"link\");i.rel=\"stylesheet\",i.type=\"text/css\",i.href=e,document.body.appendChild(i)}if(window.__INITIAL_STATE__){var jsurl=window.__INITIAL_STATE__.insertScripts[0],isBiliPlayer=window.__INITIAL_STATE__.videoData.embedPlayer,isInit=!1;function insertScript(){isInit||(isInit=!0,window.jQuery?loadAssets():loadScript(jq_url,function(){loadAssets()}))}function loadAssets(){var e=0;loadScript(header_url,function(){2===++e&&loadScript(jsurl),setSize()}),loadScript(comment_url,function(){2===++e&&loadScript(jsurl)}),loadScript(ad_url),loadLink(comment_css_url)}if(isBiliPlayer){var timeout=setTimeout(function(){clearTimeout(timeout),insertScript(),setSize()},4e3);window.PlayerMediaLoaded=function(){insertScript(),clearTimeout(timeout),window.isWide=!!document.querySelector(\".player-mode-widescreen\"),window.PlayerMediaLoaded=null,setSize(),window.performance&&window.performance.timing&&(window.performance.timing.firstscreenfinish=window.performance.timing.playerStage3||(new Date).getTime())}}else insertScript()}else document.write('<script src=\"'+jq_url+'\"><\\/script><script src=\"'+header_url+'\"><\\/script><script>setSize()<\\/script><link rel=\"stylesheet\" href=\"'+comment_css_url+'\" type=\"text/css\"><script src=\"'+comment_url+'\"><\\/script><script src=\"'+ad_url+'\"><\\/script>')</script><script type=\"text/javascript\">!function(){try{if(parent!=self&&(parent.document.domain!=document.domain||document.referrer&&!/^http(s)?:\\/\\/[.\\w-]+\\.bilibili\\.com\\//i.test(document.referrer)))throw new Error(\"can't be iframed\")}catch(e){window.open(location.href,\"_top\")}}()</script></body></html>"
}