{
	"videoinfo": {
		"aid": 7855743,
		"title": "【OVA】三年E班 第二季 课外授业篇07-08(完结)【F宅】",
		"video_review": 4379,
		"duration": null,
		"lpartinfo": [
			{
				"cid": 12890899,
				"page": 1,
				"title": "0_x264",
				"aid": 7855743,
				"duration": null,
				"video_review": 1283
			},
			{
				"cid": 12892605,
				"page": 2,
				"title": "08",
				"aid": 7855743,
				"duration": null,
				"video_review": 3096
			}
		],
		"tag": "暗杀教室,三年E班,日本动画,OVA,F宅字幕组",
		"description": "直传 嘛嘛，虽说是几集泡面，但是讲道理还是不马虎。杀老师又来当偷窥魔了。重复一点，这原来是dtv独播，我从3月到现在一直都在想办法搞个会员，但是没有如愿，BD发售了，真是大好",
		"tid": 33,
		"typename": "连载动画",
		"created": 1483543677,
		"created_at": "2017/01/04 23:27",
		"author": "空灵雨迹",
		"mid": 223902,
		"play": 582963,
		"coins": 3218,
		"review": 824,
		"favorites": 2644,
		"synctime": 1568425001.2498326
	},
	"partlist": null,
	"source": "bpd",
	"page": null
}